abstracttree/__init__.py
abstracttree/export.py
abstracttree/generics.py
abstracttree/generics.pyi
abstracttree/iterators.py
abstracttree/predicates.py
abstracttree/route.py
abstracttree/utils.py
abstracttree/adapters/__init__.py
abstracttree/adapters/adapters.py
abstracttree/adapters/heaptree.py
abstracttree/mixins/__init__.py
abstracttree/mixins/trees.py
abstracttree/mixins/views.py
abstracttree-0.2.2.dist-info/licenses/LICENSE
abstracttree-0.2.2.dist-info/METADATA
abstracttree-0.2.2.dist-info/WHEEL
abstracttree-0.2.2.dist-info/top_level.txt
abstracttree-0.2.2.dist-info/RECORD
