Metadata-Version: 2.4
Name: abstracttree
Version: 0.2.2
Summary: Abstract base classes for tree data structures
Author-email: lverweijen <lauwerund@gmail.com>
License-Expression: Apache-2.0
Project-URL: Homepage, https://github.com/lverweijen/abstracttree
Project-URL: Repository, https://github.com/lverweijen/abstracttree
Project-URL: Documentation, https://lverweijen.github.io/AbstractTree/
Project-URL: Issues, https://github.com/lverweijen/abstracttree/issues
Project-URL: Changelog, https://lverweijen.github.io/AbstractTree/CHANGES.html
Keywords: tree,datastructure,hierarchy,taxonomy,newick,graphviz,mermaid
Classifier: Intended Audience :: Developers
Classifier: Intended Audience :: Science/Research
Classifier: Operating System :: OS Independent
Classifier: Programming Language :: Python :: 3
Classifier: Programming Language :: Python :: 3.10
Classifier: Programming Language :: Python :: 3.11
Classifier: Programming Language :: Python :: 3.12
Classifier: Programming Language :: Python :: 3.13
Classifier: Typing :: Typed
Requires-Python: >=3.10
License-File: LICENSE
Provides-Extra: export
Requires-Dist: Pillow>=5.0; extra == "export"
Requires-Dist: matplotlib>=3.0; extra == "export"
Requires-Dist: svglib>=1.5.0; extra == "export"
Dynamic: license-file
